bioframe/__init__.py
bioframe/extras.py
bioframe/ops.py
bioframe/vis.py
bioframe/core/__init__.py
bioframe/core/arrops.py
bioframe/core/checks.py
bioframe/core/construction.py
bioframe/core/specs.py
bioframe/core/stringops.py
bioframe/io/__init__.py
bioframe/io/assembly.py
bioframe/io/bed.py
bioframe/io/fileops.py
bioframe/io/resources.py
bioframe/io/schemas.py
bioframe/io/data/_assemblies.yml
bioframe/io/data/ce10.seqinfo.tsv
bioframe/io/data/ce11.seqinfo.tsv
bioframe/io/data/danRer10.seqinfo.tsv
bioframe/io/data/danRer11.seqinfo.tsv
bioframe/io/data/dm3.seqinfo.tsv
bioframe/io/data/dm6.seqinfo.tsv
bioframe/io/data/hg19.cytoband.tsv
bioframe/io/data/hg19.seqinfo.tsv
bioframe/io/data/hg38.cytoband.tsv
bioframe/io/data/hg38.seqinfo.tsv
bioframe/io/data/hs1.cytoband.tsv
bioframe/io/data/hs1.seqinfo.tsv
bioframe/io/data/mm10.seqinfo.tsv
bioframe/io/data/mm39.seqinfo.tsv
bioframe/io/data/mm9.seqinfo.tsv
bioframe/io/data/sacCer3.seqinfo.tsv
bioframe/io/data/wuhCor1.seqinfo.tsv
bioframe/sandbox/clients.py
bioframe/sandbox/gtf_io.py
bioframe/sandbox/parquet_io.py
bioframe-0.8.0.dist-info/METADATA
bioframe-0.8.0.dist-info/WHEEL
bioframe-0.8.0.dist-info/licenses/LICENSE
bioframe-0.8.0.dist-info/RECORD
