Metadata-Version: 2.4
Name: bioframe
Version: 0.8.0
Summary: Operations and utilities for Genomic Interval Dataframes.
Project-URL: homepage, https://github.com/open2c/bioframe
Project-URL: documentation, https://bioframe.readthedocs.io/en/latest
Project-URL: repository, https://github.com/open2c/bioframe
Project-URL: changelog, https://github.com/open2c/bioframe/blob/main/CHANGES.md
Author-email: Open2C <open.chromosome.collective@gmail.com>
License: MIT
License-File: LICENSE
Keywords: bed,bedframe,bedtools,bioinformatics,dataframe,epigenomics,genomic ranges,genomics,interval operations,pandas,viewframe
Classifier: Development Status :: 4 - Beta
Classifier: Operating System :: OS Independent
Classifier: Programming Language :: Python
Classifier: Programming Language :: Python :: 3
Classifier: Programming Language :: Python :: 3.8
Classifier: Programming Language :: Python :: 3.9
Classifier: Programming Language :: Python :: 3.10
Classifier: Programming Language :: Python :: 3.11
Classifier: Programming Language :: Python :: 3.12
Requires-Python: >=3.8
Requires-Dist: importlib-metadata; python_version < '3.8'
Requires-Dist: importlib-resources; python_version < '3.9'
Requires-Dist: matplotlib
Requires-Dist: numpy<3,>=1.10
Requires-Dist: pandas>=1.3
Requires-Dist: pyyaml
Requires-Dist: requests
Requires-Dist: typing-extensions; python_version < '3.9'
Provides-Extra: dev
Requires-Dist: biopython; extra == 'dev'
Requires-Dist: pre-commit; extra == 'dev'
Requires-Dist: pybbi; extra == 'dev'
Requires-Dist: pysam; extra == 'dev'
Requires-Dist: pytest; extra == 'dev'
Requires-Dist: ruff; extra == 'dev'
Provides-Extra: docs
Requires-Dist: autodocsumm; extra == 'docs'
Requires-Dist: jinja2; extra == 'docs'
Requires-Dist: myst-nb; extra == 'docs'
Requires-Dist: sphinx; extra == 'docs'
Requires-Dist: sphinx-autobuild; extra == 'docs'
Requires-Dist: sphinx-rtd-theme; extra == 'docs'
Provides-Extra: test
Requires-Dist: pytest; extra == 'test'
